module_estudo/__init__.py
module_estudo/add.py
module_estudo/subtract.py
module_estudo/extras/__init__.py
module_estudo/extras/divide.py
module_estudo/extras/multiply.py
verysimplemodule/__init__.py
verysimplemodule/add.py
verysimplemodule/subtract.py
verysimplemodule/extras/__init__.py
verysimplemodule/extras/divide.py
verysimplemodule/extras/multiply.py
estudo_module-0.0.2.dist-info/METADATA
estudo_module-0.0.2.dist-info/WHEEL
estudo_module-0.0.2.dist-info/top_level.txt
estudo_module-0.0.2.dist-info/RECORD
