Metadata-Version: 2.1
Name: estudo_module
Version: 0.0.2
Summary: Meu primeiro pacote em Python
Author: Dalila Rodrigues
Author-email: <dalila.analistadesistema@gmail.com>
Keywords: python,first package
Classifier: Development Status :: 3 - Alpha
Classifier: Intended Audience :: Education
Classifier: Programming Language :: Python :: 2
Classifier: Programming Language :: Python :: 3
Classifier: Operating System :: MacOS :: MacOS X
Classifier: Operating System :: Microsoft :: Windows
